edmpy/__init__.py
edmpy-0.2.dist-info/METADATA
edmpy-0.2.dist-info/WHEEL
edmpy-0.2.dist-info/top_level.txt
edmpy-0.2.dist-info/RECORD
