Metadata-Version: 2.1
Name: edmpy
Version: 0.2
Summary: Electrodynamics at its best
Home-page: http://github.com/pradyoth-shandilya/edmpy
Author: paddyforprez
Author-email: pradyoth@ieee.org
License: MIT
Platform: UNKNOWN
